{
    "os": "Linux-6.8.0-36-generic-x86_64-with-debian-trixie-sid",
    "python": "3.7.12",
    "heartbeatAt": "2024-07-10T13:50:05.713941",
    "startedAt": "2024-07-10T13:50:05.195875",
    "docker": null,
    "cuda": null,
    "args": [],
    "state": "running",
    "program": "train_sb3_tuning.py",
    "codePathLocal": "train_sb3_tuning.py",
    "codePath": "train_sb3_tuning.py",
    "host": "chiara-ASUS-EXPERTBOOK-B3402FEA-B3402FEA",
    "username": "chiar",
    "executable": "/home/chiar/anaconda3/envs/mldl/bin/python",
    "cpu_count": 4,
    "cpu_count_logical": 8,
    "cpu_freq": {
        "current": 4013.9741249999997,
        "min": 400.0,
        "max": 4700.0
    },
    "cpu_freq_per_core": [
        {
            "current": 4099.926,
            "min": 400.0,
            "max": 4700.0
        },
        {
            "current": 4021.353,
            "min": 400.0,
            "max": 4700.0
        },
        {
            "current": 457.49,
            "min": 400.0,
            "max": 4700.0
        },
        {
            "current": 3062.164,
            "min": 400.0,
            "max": 4700.0
        },
        {
            "current": 4100.0,
            "min": 400.0,
            "max": 4700.0
        },
        {
            "current": 4081.593,
            "min": 400.0,
            "max": 4700.0
        },
        {
            "current": 820.917,
            "min": 400.0,
            "max": 4700.0
        },
        {
            "current": 3264.319,
            "min": 400.0,
            "max": 4700.0
        }
    ],
    "disk": {
        "/": {
            "total": 265.1777763366699,
            "used": 37.823062896728516
        }
    },
    "memory": {
        "total": 23.171894073486328
    }
}
