{
    "os": "Linux-6.8.0-36-generic-x86_64-with-debian-trixie-sid",
    "python": "3.7.12",
    "heartbeatAt": "2024-07-11T12:52:50.732871",
    "startedAt": "2024-07-11T12:52:50.210963",
    "docker": null,
    "cuda": null,
    "args": [],
    "state": "running",
    "program": "train_sb3_tuning.py",
    "codePathLocal": "train_sb3_tuning.py",
    "codePath": "train_sb3_tuning.py",
    "host": "chiara-ASUS-EXPERTBOOK-B3402FEA-B3402FEA",
    "username": "chiar",
    "executable": "/home/chiar/anaconda3/envs/mldl/bin/python",
    "cpu_count": 4,
    "cpu_count_logical": 8,
    "cpu_freq": {
        "current": 899.9982500000001,
        "min": 400.0,
        "max": 4700.0
    },
    "cpu_freq_per_core": [
        {
            "current": 1014.947,
            "min": 400.0,
            "max": 4700.0
        },
        {
            "current": 1595.978,
            "min": 400.0,
            "max": 4700.0
        },
        {
            "current": 400.0,
            "min": 400.0,
            "max": 4700.0
        },
        {
            "current": 650.555,
            "min": 400.0,
            "max": 4700.0
        },
        {
            "current": 1020.858,
            "min": 400.0,
            "max": 4700.0
        },
        {
            "current": 1473.664,
            "min": 400.0,
            "max": 4700.0
        },
        {
            "current": 381.913,
            "min": 400.0,
            "max": 4700.0
        },
        {
            "current": 399.872,
            "min": 400.0,
            "max": 4700.0
        }
    ],
    "disk": {
        "/": {
            "total": 265.1777763366699,
            "used": 38.56535720825195
        }
    },
    "memory": {
        "total": 23.171894073486328
    }
}
