{
    "os": "Linux-6.8.0-36-generic-x86_64-with-debian-trixie-sid",
    "python": "3.7.12",
    "heartbeatAt": "2024-07-11T13:38:29.439964",
    "startedAt": "2024-07-11T13:38:28.850670",
    "docker": null,
    "cuda": null,
    "args": [],
    "state": "running",
    "program": "udr.py",
    "codePathLocal": "udr.py",
    "codePath": "udr.py",
    "host": "chiara-ASUS-EXPERTBOOK-B3402FEA-B3402FEA",
    "username": "chiar",
    "executable": "/home/chiar/anaconda3/envs/mldl/bin/python",
    "cpu_count": 4,
    "cpu_count_logical": 8,
    "cpu_freq": {
        "current": 3302.7325,
        "min": 400.0,
        "max": 4700.0
    },
    "cpu_freq_per_core": [
        {
            "current": 3330.434,
            "min": 400.0,
            "max": 4700.0
        },
        {
            "current": 2399.975,
            "min": 400.0,
            "max": 4700.0
        },
        {
            "current": 3400.0,
            "min": 400.0,
            "max": 4700.0
        },
        {
            "current": 3400.0,
            "min": 400.0,
            "max": 4700.0
        },
        {
            "current": 2400.0,
            "min": 400.0,
            "max": 4700.0
        },
        {
            "current": 2400.0,
            "min": 400.0,
            "max": 4700.0
        },
        {
            "current": 3400.0,
            "min": 400.0,
            "max": 4700.0
        },
        {
            "current": 3399.893,
            "min": 400.0,
            "max": 4700.0
        }
    ],
    "disk": {
        "/": {
            "total": 265.1777763366699,
            "used": 38.58242416381836
        }
    },
    "memory": {
        "total": 23.171894073486328
    }
}
